smelly_python/__init__.py
smelly_python/code_smell.py
smelly_python/command_line.py
smelly_python/generator/__init__.py
smelly_python/generator/md_generator.py
smelly_python/generator/pylint_explanation_fetcher.py
smelly_python/generator/webpage_generator.py
smelly_python/resources/error.svg
smelly_python/resources/highlight.min.js
smelly_python/resources/highlightjs-line-numbers.min.js
smelly_python/resources/idea.min.css
smelly_python/resources/info.svg
smelly_python/resources/script.js
smelly_python/resources/style.css
smelly_python/resources/warning.svg
Smelly_Python-1.0.0.dist-info/LICENSE
Smelly_Python-1.0.0.dist-info/METADATA
Smelly_Python-1.0.0.dist-info/WHEEL
Smelly_Python-1.0.0.dist-info/entry_points.txt
Smelly_Python-1.0.0.dist-info/top_level.txt
Smelly_Python-1.0.0.dist-info/RECORD
